{
    "@class": "com.kony.gen.viz.model.container.KVizSegment2",
    "DNDConfig": null,
    "__parentReadjusting__": false,
    "_data_": [
        {
            "lblCategory": {
                "@class": "com.viz.ide.model.segment.SimpleTextSegmentData",
                "text": ""
            }
        }
    ],
    "_height_": {
        "type": "string",
        "value": "640dp"
    },
    "_indicator_": "none",
    "_left_": {
        "type": "string",
        "value": "4dp"
    },
    "_margin_": [
        0,
        0,
        0,
        0
    ],
    "_orientation_": 2,
    "_padding_": [
        0,
        0,
        0,
        0
    ],
    "_top_": {
        "type": "string",
        "value": "87dp"
    },
    "_width_": {
        "type": "string",
        "value": "100%"
    },
    "autogrowmode": 0,
    "canUpdateUI": true,
    "containerweight": 100,
    "counter": "00",
    "focusedindex": null,
    "focuseditem": null,
    "groupcells": false,
    "hasSections": false,
    "id": "SegmentCategories",
    "ide_onRowClick": "AS_Segment_f51123dda12f441ab97a9ae79ac62ad3",
    "info": null,
    "ipad": {
        "psp": {
            "indicator": "rowselect"
        }
    },
    "iphone": {
        "psp": {
            "indicator": "rowselect"
        }
    },
    "iscustomlayout": false,
    "isvisible": true,
    "kuid": "a2e868e7bf30434b97ffaae174dd8761",
    "masterdata": {},
    "name": "kony.ui.SegmentedUI2",
    "needpageindicator": true,
    "pageoffdotimage": "pageoffdot.png",
    "pageondotimage": "pageondot.png",
    "paginationconfig": {
        "position": "bottom"
    },
    "parent": "frmCategory",
    "pf": "frmCategory",
    "retaincontentalignment": false,
    "retainflexpositionproperties": false,
    "retainselection": false,
    "rowTemplateId": "d93d0b4bd0104c449f2c4f6ce9c67f31",
    "rowcounter": 0,
    "rowfocusskin": "sd5adaa288b2451dbf43bb7eb3a7d8f6",
    "rowskin": "sc1dbe85146c4639a5d41a38823ac4d7",
    "rowtemplate": "FlexCategory",
    "screenlevelwidget": false,
    "seccounter": 0,
    "sectionheaderskin": "s5ff6f9bad334105805379ae90476cbd",
    "selectedRows": null,
    "selectedState": false,
    "selectedindex": null,
    "selectedindices": null,
    "selecteditems": null,
    "selectedsectionindex": 0,
    "selectionbehavior": "default",
    "separatorcolor": "aaaaaa00",
    "separatorrequired": true,
    "separatorthickness": 1,
    "showscrollbars": false,
    "viewtype": "tableview",
    "vizProps": {},
    "wType": "Segment",
    "widgetalignment": 5,
    "widgetdatamap": {
        "FlexCategory": "FlexCategory",
        "lblCategory": "lblCategory"
    },
    "zindex": 1
}